xtn_tools_pro/__init__.py
xtn_tools_pro/tools.py
xtn_tools_pro/tools_flie.py
xtn_tools_pro/tools_time.py
xtn_tools_pro/_dlls/__init__.py
xtn_tools_pro/data/__init__.py
xtn_tools_pro/data/set_data_pro.py
xtn_tools_pro/db/MongoDB.py
xtn_tools_pro/db/MysqlDB.py
xtn_tools_pro/db/RedisDB.py
xtn_tools_pro/db/__init__.py
xtn_tools_pro/flask_demo/__init__.py
xtn_tools_pro/flask_demo/cli.py
xtn_tools_pro/flask_demo/ai_server_api/__init__.py
xtn_tools_pro/flask_demo/ai_server_api/recognize_ai_server_pro.py
xtn_tools_pro/flask_demo/ai_server_api/app/__init__.py
xtn_tools_pro/flask_demo/ai_server_api/app/app.py
xtn_tools_pro/flask_demo/templates/.gitignore
xtn_tools_pro/flask_demo/templates/Dockerfile
xtn_tools_pro/flask_demo/templates/README.md
xtn_tools_pro/flask_demo/templates/__init__.py
xtn_tools_pro/flask_demo/templates/docker-compose.yml
xtn_tools_pro/flask_demo/templates/recognize_ai_server_pro.py
xtn_tools_pro/flask_demo/templates/requirements.txt
xtn_tools_pro/flask_demo/templates/server_run.py
xtn_tools_pro/flask_demo/templates/uwsgi.ini
xtn_tools_pro/flask_demo/templates/app/__init__.py
xtn_tools_pro/flask_demo/templates/app/app.py
xtn_tools_pro/flask_demo/templates/app/api/__init__.py
xtn_tools_pro/flask_demo/templates/app/api/v1/__init__.py
xtn_tools_pro/flask_demo/templates/app/api/v1/demo.py
xtn_tools_pro/flask_demo/templates/app/config/__init__.py
xtn_tools_pro/flask_demo/templates/app/config/secure.py
xtn_tools_pro/flask_demo/templates/app/config/setting.py
xtn_tools_pro/flask_demo/templates/app/libs/__init__.py
xtn_tools_pro/flask_demo/templates/app/libs/base.py
xtn_tools_pro/flask_demo/templates/app/libs/error.py
xtn_tools_pro/flask_demo/templates/app/libs/error_code.py
xtn_tools_pro/flask_demo/templates/app/libs/redprint.py
xtn_tools_pro/flask_demo/templates/app/libs/token_auth.py
xtn_tools_pro/flask_demo/templates/app/models/__init__.py
xtn_tools_pro/flask_demo/templates/app/models/base.py
xtn_tools_pro/flask_demo/templates/app/models/redis_demo.py
xtn_tools_pro-1.0.1.5.7.dist-info/LICENSE
xtn_tools_pro-1.0.1.5.7.dist-info/METADATA
xtn_tools_pro-1.0.1.5.7.dist-info/WHEEL
xtn_tools_pro-1.0.1.5.7.dist-info/entry_points.txt
xtn_tools_pro-1.0.1.5.7.dist-info/top_level.txt
xtn_tools_pro-1.0.1.5.7.dist-info/RECORD
