Metadata-Version: 2.1
Name: xtn-tools-pro
Version: 1.0.1.5.7
Summary: xtn 开发工具
Author: xtn
Author-email: czw011122@gmail.com
Classifier: Programming Language :: Python :: 3
Requires-Python: >=3.7
License-File: LICENSE
Requires-Dist: pymongo
Requires-Dist: redis
Requires-Dist: pymysql
Requires-Dist: dbutils
Requires-Dist: colorlog
Requires-Dist: requests
Requires-Dist: Faker
Requires-Dist: PyJWT
Requires-Dist: tqdm
Requires-Dist: fabric
Requires-Dist: pyotp
Requires-Dist: pycryptodome
Requires-Dist: psutil
